dephell_discover-0.2.10.dist-info/dependency_links.txt
dephell_discover-0.2.10.dist-info/entry_points.txt
dephell_discover-0.2.10.dist-info/METADATA
dephell_discover-0.2.10.dist-info/top_level.txt
dephell_discover-0.2.10.dist-info/WHEEL
dephell_discover/_constants.py
dephell_discover/_package.py
dephell_discover/_data.py
dephell_discover/_cached_propery.py
dephell_discover/__init__.py
dephell_discover/_root.py
dephell_discover/_metainfo.py
dephell_discover/_line.py
dephell_discover-0.2.10.dist-info/LICENSE
dephell_discover-0.2.10.dist-info/RECORD