Metadata-Version: 2.1
Name: dephell-discover
Version: 0.2.10
Summary: Find project modules and data files (packages and package_data for setup.py).
Project-URL: Repository, https://github.com/dephell/dephell_discover
Author: Gram
Author-email: master_fess@mail.ru
License: MIT
Requires-Python: >=3.5
Keywords: dephell,packaging,dependency,dependencies,setuptools,packages,finder
Classifier: Development Status :: 4 - Beta
Classifier: Environment :: Console
Classifier: Framework :: Setuptools Plugin
Classifier: Intended Audience :: Developers
Classifier: License :: OSI Approved :: MIT License
Classifier: Programming Language :: Python
Classifier: Topic :: Software Development :: Libraries :: Python Modules
Requires-Dist: attrs
